LICENSE
MANIFEST.in
README.md
setup.py
nocode_utils/__init__.py
nocode_utils/config.py
nocode_utils.egg-info/PKG-INFO
nocode_utils.egg-info/SOURCES.txt
nocode_utils.egg-info/dependency_links.txt
nocode_utils.egg-info/top_level.txt
nocode_utils/database_utils/DBProcessor.py
nocode_utils/database_utils/__init__.py
nocode_utils/feishu_utils/AESCipher.py
nocode_utils/feishu_utils/__init__.py
nocode_utils/http_utils/__init__.py
nocode_utils/nlp_utils/Simbert.py
nocode_utils/nlp_utils/__init__.py
nocode_utils/nlp_utils/common.py
nocode_utils/nlp_utils/data_augmentation.py
nocode_utils/nlp_utils/data_preprocess.py
nocode_utils/threading_utils/Threads.py
nocode_utils/threading_utils/__init__.py