Metadata-Version: 2.1
Name: nocode-utils
Version: 1.3.2
Summary: 封装常用函数和类
Home-page: https://github.com/jasonhhao
Author: JasonHao
Author-email: jason.hehao@gmail.com
Platform: all
Classifier: Intended Audience :: Developers
Classifier: Operating System :: OS Independent
Classifier: Natural Language :: Chinese (Simplified)
Classifier: Programming Language :: Python :: 3
Classifier: Topic :: Software Development :: Libraries
License-File: LICENSE
